{
  "resolvedId": "/Users/mohammadrassoulzadeh/Documents/project/marktify/front/assets/icons/iconsax/linear/microphone.svg?raw",
  "transforms": [
    {
      "name": "vite:asset",
      "result": "export default \"<svg width=\\\"24\\\" height=\\\"24\\\" viewBox=\\\"0 0 24 24\\\" fill=\\\"none\\\" xmlns=\\\"http://www.w3.org/2000/svg\\\">\\n<path d=\\\"M12 19C15.31 19 18 16.31 18 13V8C18 4.69 15.31 2 12 2C8.69 2 6 4.69 6 8V13C6 16.31 8.69 19 12 19Z\\\" stroke=\\\"#292D32\\\" stroke-width=\\\"1.5\\\" stroke-linecap=\\\"round\\\" stroke-linejoin=\\\"round\\\"/>\\n<path d=\\\"M3 11V13C3 17.97 7.03 22 12 22C16.97 22 21 17.97 21 13V11\\\" stroke=\\\"#292D32\\\" stroke-width=\\\"1.5\\\" stroke-linecap=\\\"round\\\" stroke-linejoin=\\\"round\\\"/>\\n<path d=\\\"M9.11011 7.47993C10.8901 6.82993 12.8301 6.82993 14.6101 7.47993\\\" stroke=\\\"#292D32\\\" stroke-width=\\\"1.5\\\" stroke-linecap=\\\"round\\\" stroke-linejoin=\\\"round\\\"/>\\n<path d=\\\"M10.03 10.4799C11.23 10.1499 12.5 10.1499 13.7 10.4799\\\" stroke=\\\"#292D32\\\" stroke-width=\\\"1.5\\\" stroke-linecap=\\\"round\\\" stroke-linejoin=\\\"round\\\"/>\\n</svg>\\n\"",
      "start": 1746483915216,
      "end": 1746483915222,
      "sourcemaps": null
    },
    {
      "name": "nuxt:components-loader-pre",
      "start": 1746483915222,
      "end": 1746483915222,
      "order": "pre"
    },
    {
      "name": "nuxt:layer-aliasing",
      "start": 1746483915222,
      "end": 1746483915222,
      "order": "pre"
    },
    {
      "name": "nuxt:server-devonly:transform",
      "start": 1746483915222,
      "end": 1746483915222,
      "order": "pre"
    },
    {
      "name": "vite:esbuild",
      "start": 1746483915222,
      "end": 1746483915222,
      "order": "normal"
    },
    {
      "name": "vite:worker",
      "start": 1746483915222,
      "end": 1746483915222,
      "order": "normal-normal"
    },
    {
      "name": "vite:vue",
      "start": 1746483915222,
      "end": 1746483915222,
      "order": "normal"
    },
    {
      "name": "vite:vue-jsx",
      "start": 1746483915222,
      "end": 1746483915222,
      "order": "normal"
    },
    {
      "name": "replace",
      "start": 1746483915222,
      "end": 1746483915222,
      "order": "normal"
    },
    {
      "name": "nuxt:remove-plugin-metadata",
      "start": 1746483915222,
      "end": 1746483915222,
      "order": "normal"
    },
    {
      "name": "nuxt:prehydrate-transform",
      "start": 1746483915222,
      "end": 1746483915222,
      "order": "normal"
    },
    {
      "name": "nuxt:module-preload-polyfill",
      "start": 1746483915222,
      "end": 1746483915222,
      "order": "normal"
    },
    {
      "name": "replace",
      "start": 1746483915222,
      "end": 1746483915222,
      "order": "normal"
    },
    {
      "name": "ssr-styles",
      "start": 1746483915222,
      "end": 1746483915222,
      "order": "normal"
    },
    {
      "name": "vite:define",
      "start": 1746483915222,
      "end": 1746483915222,
      "order": "normal-normal"
    },
    {
      "name": "vite:build-html",
      "start": 1746483915222,
      "end": 1746483915222,
      "order": "normal-normal"
    },
    {
      "name": "vite:worker-import-meta-url",
      "start": 1746483915222,
      "end": 1746483915222,
      "order": "normal-normal"
    },
    {
      "name": "vite:asset-import-meta-url",
      "start": 1746483915222,
      "end": 1746483915222,
      "order": "normal-normal"
    },
    {
      "name": "vite:dynamic-import-vars",
      "start": 1746483915222,
      "end": 1746483915222,
      "order": "normal-normal"
    },
    {
      "name": "vite:import-glob",
      "start": 1746483915222,
      "end": 1746483915222,
      "order": "normal-normal"
    },
    {
      "name": "nuxt:composable-keys",
      "start": 1746483915222,
      "end": 1746483915222,
      "order": "post"
    },
    {
      "name": "nuxt:head:unhead-imports",
      "start": 1746483915222,
      "end": 1746483915222,
      "order": "post"
    },
    {
      "name": "nuxt:imports-transform",
      "start": 1746483915222,
      "end": 1746483915222,
      "order": "post"
    },
    {
      "name": "unctx:transform",
      "start": 1746483915222,
      "end": 1746483915222,
      "order": "post"
    },
    {
      "name": "nuxt:pages-macros-transform",
      "start": 1746483915222,
      "end": 1746483915222,
      "order": "post"
    },
    {
      "name": "nuxt:runtime-paths-dep",
      "start": 1746483915222,
      "end": 1746483915222,
      "order": "post"
    },
    {
      "name": "nuxt:route-injection-plugin",
      "start": 1746483915222,
      "end": 1746483915222,
      "order": "post"
    },
    {
      "name": "nuxt:components:imports",
      "start": 1746483915222,
      "end": 1746483915222,
      "order": "post"
    },
    {
      "name": "nuxt:components-loader",
      "start": 1746483915222,
      "end": 1746483915222,
      "order": "post"
    },
    {
      "name": "nuxt:tree-shake-composables:transform",
      "start": 1746483915222,
      "end": 1746483915222,
      "order": "post"
    },
    {
      "name": "vite:build-import-analysis",
      "start": 1746483915222,
      "end": 1746483915222,
      "order": "normal-normal"
    },
    {
      "name": "vite:reporter",
      "start": 1746483915222,
      "end": 1746483915222,
      "order": "normal"
    }
  ]
}
